{
  "id": "dyaus",
  "mythology": "hindu",
  "attributes": {},
  "mythologyStories": {},
  "tags": [
    "hindu",
    "deity"
  ],
  "worship": {},
  "name": "Dyaus Pita - Hindu Mythology",
  "relationships": {},
  "description": "",
  "interlinks": {
    "cross_cultural_parallels": [
      {
        "name": "Zeus",
        "url": "../../greek/deities/zeus.html",
        "mythology": "Greek"
      },
      {
        "name": "Jupiter",
        "url": "../../roman/deities/jupiter.html",
        "mythology": "Roman"
      },
      {
        "name": "Odin",
        "url": "../../norse/deities/odin.html",
        "mythology": "Norse"
      },
      {
        "name": "Perun",
        "url": "../../../index.html",
        "mythology": "Slavic"
      }
    ],
    "sacred_items": [
      {
        "name": "Prithvi",
        "url": "prithvi.html",
        "type": "Earth Mother"
      },
      {
        "name": "Indra",
        "url": "indra.html",
        "type": "Son"
      }
    ],
    "archetype": {
      "name": "☁️ SKY FATHER",
      "description": "Dyaus Pita embodies the primordial Sky Father archetype - the celestial patriarch who rules the heavens and partners with Earth Mother to create all life.",
      "url": "../../../archetypes/sky-father/"
    }
  },
  "icon": "☁️",
  "subtitle": "",
  "type": "deity",
  "cssColors": {},
  "searchTerms": [
    "pita",
    "-",
    "mythology",
    "hindu",
    "dyaus",
    "dyaus pita - hindu mythology"
  ],
  "seeAlso": [
    {
      "url": "prithvi.html",
      "text": "🌍Prithvi"
    },
    {
      "url": "indra.html",
      "text": "⚡Indra"
    },
    {
      "url": "../cosmology/creation.html",
      "text": "🌌Vedic Cosmology"
    },
    {
      "url": "../texts/index.html",
      "text": "📜Rigveda"
    },
    {
      "url": "../../../archetypes/sky-father/",
      "text": "🎭Sky Father Archetype"
    }
  ],
  "createdAt": {
    "_seconds": 1765798411,
    "_nanoseconds": 557000000
  },
  "metadata": {
    "extractionVersion": "2.6",
    "uploadedBy": "migration-script-v3.4",
    "completenessScore": 10,
    "sourceFile": "mythos/hindu/deities/dyaus.html",
    "uploadedAt": {
      "_seconds": 1765798411,
      "_nanoseconds": 557000000
    }
  },
  "updatedAt": {
    "_seconds": 1765798411,
    "_nanoseconds": 557000000
  }
}