{
  "id": "mary-magdalene",
  "mythology": "christian",
  "attributes": {},
  "mythologyStories": {},
  "tags": [
    "other",
    "christian"
  ],
  "worship": {},
  "name": "Mary Magdalene - Apostle to the Apostles - World Mythos Explorer",
  "relationships": {},
  "description": "",
  "interlinks": {},
  "icon": "",
  "subtitle": "",
  "type": "other",
  "cssColors": {},
  "searchTerms": [
    "apostle",
    "mary magdalene - apostle to the apostles - world mythos explorer",
    "world",
    "-",
    "to",
    "magdalene",
    "explorer",
    "the",
    "apostles",
    "mary",
    "mythos"
  ],
  "seeAlso": [],
  "createdAt": {
    "_seconds": 1765798398,
    "_nanoseconds": 191000000
  },
  "metadata": {
    "extractionVersion": "2.6",
    "uploadedBy": "migration-script-v3.4",
    "completenessScore": 10,
    "sourceFile": "mythos/christian/gnostic/mary-magdalene.html",
    "uploadedAt": {
      "_seconds": 1765798398,
      "_nanoseconds": 191000000
    }
  },
  "updatedAt": {
    "_seconds": 1765798398,
    "_nanoseconds": 191000000
  }
}