{
  "id": "white-buffalo-woman",
  "mythology": "native_american",
  "attributes": {},
  "mythologyStories": {},
  "tags": [
    "native_american",
    "other"
  ],
  "worship": {},
  "name": "White Buffalo Calf Woman - Lakota Sacred Being",
  "relationships": {},
  "description": "",
  "interlinks": {
    "cross_cultural_parallels": [
      {
        "name": "Virgin Mary",
        "url": "../../../mythos/christian/index.html",
        "mythology": "Christian"
      },
      {
        "name": "Quan Yin",
        "url": "../../buddhist/deities/guanyin.html",
        "mythology": "Buddhist"
      },
      {
        "name": "Isis",
        "url": "../../../mythos/egyptian/deities/isis.html",
        "mythology": "Egyptian"
      },
      {
        "name": "Lakshmi",
        "url": "../../../mythos/hindu/deities/index.html",
        "mythology": "Hindu"
      },
      {
        "name": "Brigid",
        "url": "../../../mythos/celtic/deities/brigid.html",
        "mythology": "Celtic"
      }
    ],
    "sacred_items": [
      {
        "name": "Spider Woman",
        "url": "spider-woman.html"
      }
    ],
    "archetype": {
      "name": "DIVINE MESSENGER / SACRED FEMININE",
      "description": "White Buffalo Calf Woman embodies the divine feminine messenger who brings sacred gifts to transform a people.",
      "url": "../../../archetypes/index.html"
    }
  },
  "icon": "",
  "subtitle": "",
  "type": "other",
  "cssColors": {
    "secondary": "#B8860B",
    "primary": "#F5F5F5"
  },
  "searchTerms": [
    "woman",
    "buffalo",
    "white buffalo calf woman - lakota sacred being",
    "calf",
    "-",
    "being",
    "lakota",
    "white",
    "sacred"
  ],
  "seeAlso": [
    {
      "url": "spider-woman.html",
      "text": "🕷Spider Woman"
    },
    {
      "url": "thunderbird.html",
      "text": "🦅Thunderbird"
    },
    {
      "url": "coyote.html",
      "text": "🐶Coyote"
    },
    {
      "url": "../index.html",
      "text": "🌈Native American Home"
    }
  ],
  "createdAt": {
    "_seconds": 1765798420,
    "_nanoseconds": 709000000
  },
  "metadata": {
    "extractionVersion": "2.6",
    "uploadedBy": "migration-script-v3.4",
    "completenessScore": 10,
    "sourceFile": "mythos/native_american/spirits/white-buffalo-woman.html",
    "uploadedAt": {
      "_seconds": 1765798420,
      "_nanoseconds": 709000000
    }
  },
  "updatedAt": {
    "_seconds": 1765798420,
    "_nanoseconds": 709000000
  }
}