{
  "id": "sumerian_gilgamesh",
  "name": "Sumerian/Babylonian Mythology",
  "significance": [
    "Oldest known epic literature",
    "Establishes hero's journey archetype",
    "Explores universal themes still resonant today",
    "Influenced Biblical and Greek traditions",
    "Preserves ancient Mesopotamian worldview"
  ],
  "type": "concept",
  "_enhanced": true,
  "primarySources": [
    "Standard Babylonian Version (Sin-leqi-unninni)",
    "Old Babylonian tablets",
    "Sumerian Gilgamesh poems",
    "Nineveh library tablets"
  ],
  "narrativeStructure": {
    "act4_hubris": "Rejecting Ishtar, slaying Bull of Heaven, angering gods",
    "act7_failure": "Fails tests, loses plant of immortality, returns to Uruk",
    "act6_quest": "Journey to Utnapishtim seeking immortality secret",
    "resolution": "Acceptance of mortality, finding meaning in legacy and accomplishment",
    "act1_tyrant": "Gilgamesh oppresses Uruk - gods create Enkidu as rival/equal",
    "act2_friendship": "Epic battle transforms into deep friendship - first great literary friendship",
    "act5_loss": "Enkidu dies as punishment - Gilgamesh confronts mortality",
    "act3_glory": "Quest to Cedar Forest, slaying Humbaba, cutting sacred trees"
  },
  "participants": [
    "Gilgamesh - The hero king of Uruk",
    "Enkidu - Wild man companion",
    "Ishtar/Inanna - Goddess of love and war",
    "Enlil - Lord of wind and storm",
    "Ea/Enki - God of wisdom",
    "Shamash - Sun god who aids heroes",
    "Utnapishtim - Immortal flood survivor",
    "Humbaba - Guardian of Cedar Forest"
  ],
  "mythology": "sumerian",
  "filename": "gilgamesh",
  "majorThemes": {
    "grief": "Overwhelming power of loss to transform personality and priorities",
    "ambitionLimits": "Some quests (immortality) are beyond human reach",
    "mortality": "Inescapable human condition - even heroes must die",
    "civilization": "Enkidu's transformation from wild man to civilized human",
    "friendship": "Transformative power of deep companionship - violence to love",
    "legacy": "Immortality through accomplishments, city-building, story"
  },
  "displayName": "𒄑𒂆𒈦 The Epic of Gilgamesh",
  "relatedConcepts": [
    "Death and Mortality - Universal theme",
    "The Hero's Journey - Quest narrative",
    "Friendship - Transformative bonds",
    "The Great Flood - Cross-cultural mythology",
    "Inanna's Descent - Underworld journey",
    "Sumerian Deities - The Anunnaki pantheon",
    "The Odyssey - Later Greek epic parallel"
  ],
  "historicalContext": {
    "historicalKing": "Gilgamesh may have been actual king of Uruk (c. 2700 BCE)",
    "rediscovery": "Tablets discovered in Nineveh library of Ashurbanipal (1849-1854)",
    "standardVersion": "Sin-leqi-unninni version (c. 1300-1000 BCE) - most complete",
    "origin": "Sumerian poems about Gilgamesh (c. 2100 BCE) compiled into Akkadian epic (c. 1800-1600 BCE)",
    "culturalImpact": "Influenced Biblical flood narrative and hero's journey archetype"
  },
  "_uploadedAt": "2025-12-25T15:46:38.560107",
  "metadata": {
    "source": "html_parser",
    "updatedAt": "2025-12-25T20:00:00.000Z",
    "enhancedBy": "Agent_16_ConceptPolishing",
    "verified": false,
    "createdBy": "system",
    "createdAt": "2025-12-13T02:52:39.664Z",
    "sourceFile": "mythos/sumerian/myths/gilgamesh.html",
    "enhancementDate": "2025-12-25T20:00:00.000Z"
  },
  "description": "The Epic of Gilgamesh is the oldest known work of epic literature, originating in ancient Mesopotamia around 2100 BCE. It tells the story of Gilgamesh, the mighty king of Uruk, and his quest for immortality following the death of his beloved companion Enkidu. The epic explores timeless themes of friendship, mortality, legacy, and the limits of human ambition, establishing narrative patterns that would echo through world literature for millennia.",
  "enhancedBy": "agent8-v2",
  "updatedAt": "2025-12-26T05:15:10.589Z"
}